{"executed_at":"2026-03-26T01:52:46Z","data":[{"tag":"b8522","published_at":"2026-03-25T17:28:34Z","body":"llama-bench: print `-n-cpu-moe` when offloaded layers > 1 (#20984)"},{"tag":"b8519","published_at":"2026-03-25T17:14:18Z","body":"jinja: fix macro with kwargs (#20960)\n\n* jinja: fix macro with kwargs\n\n* Apply suggestions from code review\n\nCo-authored-by: Sigbjørn Skjæret <sigbjorn.skjaeret@scala.com>\n\n* fix newline problem\n\n---------\n\nCo-authored-by: Sigbjørn Skjæret <sigbjorn.skjaeret@scala.com>"},{"tag":"b8517","published_at":"2026-03-25T16:54:15Z","body":"llama: fix llama-model-saver (#20503)\n\n* llama : add fd-based model loading via llama_model_load_from_fd\n\n* llama : address review feedback for fd-based model loading\n\n* llama : use FILE pointer instead of fd in public API\n\n* llama : use FILE pointer consistently, address review feedback\n\n* fixup\n\n* fix tensor names\n\n* fix llama-model-saver\n\n* roundtrip tests\n\n* fixup\n\n* refactor tests\n\n* fix prints\n\n* fix model saving\n\n* fix CI, disable Chameleon\n\n* print seed\n\n---------\n\nCo-authored-by: Siddhesh2377 <siddheshsonar2377@gmail.com>"},{"tag":"b8514","published_at":"2026-03-25T12:15:31Z","body":"android : fix-pointer-dangling (#20974)"},{"tag":"b8513","published_at":"2026-03-25T11:56:32Z","body":"sycl : fix wrong variable check by assert (#20903)\n\n* fix wrong variable check by assert\n\n* use GGML api"}]}
